{
	"ZW": {
		"crews": [
			{
				"id": 0112,
				"name": "于波",
				"sex": "",	
				"station": "书记",	
				"tenure": "1976.10-1979.03",
				"more": {
					"photo": "url",
					"Profile": "..."
				}
			},{
				"id": 0113,
				"name": "朱清明",
				"sex": "",	
				"station": "书记",	
				"tenure": "1980.12-1983.07",
				"more": {
					"photo": "url",
					"Profile": "..."
				}
			},{
				"id": 0114,
				"name": "王恩科",
				"sex": "",	
				"station": "书记",	
				"tenure": "1983.08-1985.12",
				"more": {
					"photo": "url",
					"Profile": "..."
				}
			},{
				"id": 0115,
				"name": "李生芳",
				"sex": "",	
				"station": "书记",	
				"tenure": "1985.12-1986.05",
				"more": {
					"photo": "url",
					"Profile": "..."
				}
			},{
				"id": 0116,
				"name": "侯少卿",
				"sex": "",	
				"station": "副书记",	
				"tenure": "1980.12-1983.05",
				"more": {
					"photo": "url",
					"Profile": "..."
				}
			},{
				"id": 0117,
				"name": "伊本干",
				"sex": "",	
				"station": "副书记",	
				"tenure": "1980.12-1982.06",
				"more": {
					"photo": "url",
					"Profile": "..."
				}
			},{
				"id": 0118,
				"name": "濮九康",
				"sex": "",	
				"station": "副书记",	
				"tenure": "1980.12-1983.02",
				"more": {
					"photo": "url",
					"Profile": "..."
				}
			},{
				"id": 0119,
				"name": "王文明",
				"sex": "",	
				"station": "副书记",	
				"tenure": "1983.08-1986.05",
				"more": {
					"photo": "url",
					"Profile": "..."
				}
			},{
				"id": 0120,
				"name": "翟松天",
				"sex": "",	
				"station": "副书记",	
				"tenure": "1983.08-1986.05",
				"more": {
					"photo": "url",
					"Profile": "..."
				}
			},{
				"id": 0121,
				"name": "宋维祯",
				"sex": "",
				"station": "副书记",	
				"tenure": "1983.08-1986.05",
				"more": {
					"photo": "url",
					"Profile": "..."
				}
			},{
				"id": 0122,
				"name": "李生芳",
				"sex": "",
				"station": "副书记",	
				"tenure": "1985.06-1985.12",
				"more": {
					"photo": "url",
					"Profile": "..."
				}
			},{
				"id": 0123,
				"name": "葛凡",
				"sex": "",	
				"station": "副书记",	
				"tenure": "1986.03-1986.05",
				"more": {
					"photo": "url",
					"Profile": "..."
				}
			},{
				"id": 0124,
				"name": "陆纯",
				"sex": "",	
				"station": "常委",	
				"tenure": "1980.12-1983.2",
				"more": {
					"photo": "url",
					"Profile": "..."
				}
			},{
				"id": 0125,
				"name": "巴桑卓玛",
				"sex": "",	
				"station": "常委",	
				"tenure": "1980.12-1983.07",
				"more": {
					"photo": "url",
					"Profile": "..."
				}
			},{
				"id": 0126,
				"name": "邓芳明",
				"sex": "",	
				"station": "常委",	
				"tenure": "1980.12-1981.10",
				"more": {
					"photo": "url",
					"Profile": "..."
				}
			},{
				"id": 0127,
				"name": "李生芳",
				"sex": "",	
				"station": "常委",	
				"tenure": "1980.12-1983.08",
				"more": {
					"photo": "url",
					"Profile": "..."
				}
			},{
				"id": 0128,
				"name": "陈希濂",
				"sex": "",	
				"station": "常委",	
				"tenure": "1981.10-1983.05",
				"more": {
					"photo": "url",
					"Profile": "..."
				}
			},{
				"id": 0129,
				"name": "周宽民",
				"sex": "",	
				"station": "常委",	
				"tenure": "1983.08-1986.02",
				"more": {
					"photo": "url",
					"Profile": "..."
				}
			},{
				"id": 0130,
				"name": "尕帕",
				"sex": "",	
				"station": "常委",	
				"tenure": "1983.08-1986.05",
				"more": {
					"photo": "url",
					"Profile": "..."
				}
			},{
				"id": 0131,
				"name": "吴玉贤",
				"sex": "",	
				"station": "常委",	
				"tenure": "1983.08-1986.03",
				"more": {
					"photo": "url",
					"Profile": "..."
				}
			},{
				"id": 0132,
				"name": "李培兰",
				"sex": "",	
				"station": "常委",	
				"tenure": "1983.08-1986.05",
				"more": {
					"photo": "url",
					"Profile": "..."
				}
			},{
				"id": 0133,
				"name": "乔正孝",
				"sex": "",	
				"station": "常委",	
				"tenure": "1983.08-1986.05",
				"more": {
					"photo": "url",
					"Profile": "..."
				}
			}
		],
		"period": 6,
		"main_duties": "...",
		"snapshot": ["url-1","url-2"]	
	},
	"RD": {
		"crews": [
			{
				"id": 0134,
				"name": "濮九康",
				"sex": "",	
				"station": "主任",	
				"tenure": "1981.05-1983.12",
				"more": {
					"photo": "url",
					"Profile": "..."
				}
			},{
				"id": 0135,
				"name": "弋复元",
				"sex": "",	
				"station": "主任",	
				"tenure": "1983.12-1986.06",
				"more": {
					"photo": "url",
					"Profile": "..."
				}
			},{
				"id": 0136,
				"name": "司维洪",
				"sex": "",	
				"station": "副主任",	
				"tenure": "1981.5-1986.6",
				"more": {
					"photo": "url",
					"Profile": "..."
				}
			},{
				"id": 0137,
				"name": "格桑秋吉",
				"sex": "",	
				"station": "副主任",	
				"tenure": "1981.05-1986.06",
				"more": {
					"photo": "url",
					"Profile": "..."
				}
			},{
				"id": 0138,
				"name": "弋复元",
				"sex": "",	
				"station": "副主任",	
				"tenure": "1981.05-1983.12",
				"more": {
					"photo": "url",
					"Profile": "..."
				}
			},,{
				"id": 0139,
				"name": "米扎西",
				"sex": "",	
				"station": "副主任",	
				"tenure": "1983.12-1986.06",
				"more": {
					"photo": "url",
					"Profile": "..."
				}
			},{
				"id": 0140,
				"name": "巴桑卓玛",
				"sex": "",	
				"station": "副主任",	
				"tenure": "1983.12-1986.06",
				"more": {
					"photo": "url",
					"Profile": "..."
				}
			},{
				"id": 0141,
				"name": "王文治",
				"sex": "",	
				"station": "副主任",	
				"tenure": "1983.12-1986.06",
				"more": {
					"photo": "url",
					"Profile": "..."
				}
			},{
				"id": 0142,
				"name": "秋哇",
				"sex": "",	
				"station": "副主任",	
				"tenure": "1983.12-1986.06",
				"more": {
					"photo": "url",
					"Profile": "..."
				}
			}
		],
		"period": 6,
		"main_duties": "...",
		"snapshot": []
	},
	"ZF": {
		"crews": [
			{
				"id": 0143,
				"name": "伊本干",
				"sex": "",	
				"station": "州长",	
				"tenure": "1981.05-1982.06",
				"more": {
					"photo": "url",
					"Profile": "..."
				}
			},{
				"id": 0144,
				"name": "王文明",
				"sex": "",	
				"station": "州长",	
				"tenure": "1983.08-1986.06",
				"more": {
					"photo": "url",
					"Profile": "..."
				}
			},{
				"id": 0145,
				"name": "才培多杰",
				"sex": "",	
				"station": "副州长",	
				"tenure": "1981.05-1986.06",
				"more": {
					"photo": "url",
					"Profile": "..."
				}
			},{
				"id": 0146,
				"name": "本派",
				"sex": "",	
				"station": "副州长",	
				"tenure": "1981.05-1986.06",
				"more": {
					"photo": "url",
					"Profile": "..."
				}
			},{
				"id": 0147,
				"name": "彭措旺扎",
				"sex": "",	
				"station": "副州长",	
				"tenure": "1981.05-1986.06",
				"more": {
					"photo": "url",
					"Profile": "..."
				}
			},{
				"id": 0148,
				"name": "蒋国良",
				"sex": "",	
				"station": "副州长",	
				"tenure": "1981.05-1986.06",
				"more": {
					"photo": "url",
					"Profile": "..."
				}
			},{
				"id": 0149,
				"name": "何梁初",
				"sex": "",	
				"station": "副州长",	
				"tenure": "1983-1986.06",
				"more": {
					"photo": "url",
					"Profile": "..."
				}
			},{
				"id": 0150,
				"name": "杨允习",
				"sex": "",	
				"station": "副州长",	
				"tenure": "1983-1986.06",
				"more": {
					"photo": "url",
					"Profile": "..."
				}
			},{
				"id": 0151,
				"name": "高昭平",
				"sex": "",	
				"station": "副州长",	
				"tenure": "1986.03-1986.06",
				"more": {
					"photo": "url",
					"Profile": "..."
				}
			}
		],
		"period": 6,
		"main_duties": "...",
		"snapshot": ["url-1","url-2"]
	},
	"ZX": {
		"crews": [
			{
				"id": 0152,
				"name": "于波",
				"sex": "",	
				"station": "主席",	
				"tenure": "1978.07-1979.03",
				"more": {
					"photo": "url",
					"Profile": "..."
				}
			},{
				"id": 0153,
				"name": "朱清明",
				"sex": "",	
				"station": "副主席",	
				"tenure": "1978.07-1981.05",
				"more": {
					"photo": "url",
					"Profile": "..."
				}
			},{
				"id": 0154,
				"name": "扎西才仁",
				"sex": "",	
				"station": "副主席",	
				"tenure": "1978.07-1978.12",
				"more": {
					"photo": "url",
					"Profile": "..."
				}
			},{
				"id": 0155,
				"name": "本派",
				"sex": "",	
				"station": "副主席",	
				"tenure": "1978.07-1981.05",
				"more": {
					"photo": "url",
					"Profile": "..."
				}
			}
		],
		"period": 6,
		"main_duties": "...",
		"snapshot": ["url-1","url-2"]
	}
}